PyCASC/__init__.py
PyCASC/download.py
PyCASC/launcher.py
PyCASC/rootfiles/__init__.py
PyCASC/rootfiles/diablo3.py
PyCASC/rootfiles/hearthstone.py
PyCASC/rootfiles/mndx.py
PyCASC/rootfiles/ow.py
PyCASC/rootfiles/warcraft3.py
PyCASC/rootfiles/wow.py
PyCASC/utils/CASCUtils.py
PyCASC/utils/blizzutils.py
PyCASC-0.1.0.dist-info/LICENSE.txt
PyCASC-0.1.0.dist-info/METADATA
PyCASC-0.1.0.dist-info/WHEEL
PyCASC-0.1.0.dist-info/top_level.txt
PyCASC-0.1.0.dist-info/RECORD
