Metadata-Version: 2.1
Name: PyCASC
Version: 0.1.0
Summary: Pure Python CASC file structure reader
Home-page: https://github.com/raidandfade/pycasc
Author: raidandfade
Author-email: business@gocode.it
License: UNKNOWN
Platform: UNKNOWN
Classifier: Programming Language :: Python :: 3
Classifier: License :: OSI Approved :: MIT License
Classifier: Operating System :: OS Independent
Requires-Dist: requests (==2.21.0)
Requires-Dist: salsa20 (==0.3.0)
